{"function": "language", "filename": "NavigatorLanguage"}
{"function": "languages", "filename": "Navigator.cpp"}
{"function": "menubar", "filename": "LocalDOMWindow.cpp"}
{"function": "menubar", "filename": "RemoteDOMWindow.cpp"}
{"function": "print", "filename": "LocalDOMWindow.cpp"}
{"function": "print", "filename": "RemoteDOMWindow.cpp"}
{"function": "applicationCache", "filename": "LocalDOMWindow.cpp"}
{"function": "applicationCache", "filename": "RemoteDOMWindow.cpp"}
{"function": "assign", "filename": "Location.cpp"}
{"function": "replace", "filename": "Location.cpp"}
{"function": "statusbar", "filename": "LocalDOMWindow.cpp"}
{"function": "statusbar", "filename": "RemoteDOMWindow.cpp"}
{"function": "locationbar", "filename": "LocalDOMWindow.cpp"}
{"function": "locationbar", "filename": "RemoteDOMWindow.cpp"}
{"function": "href", "filename": "Location.cpp"}
{"function": "alert", "filename": "LocalDOMWindow.cpp"}
{"function": "alert", "filename": "RemoteDOMWindow.cpp"}
{"function": "status", "filename": "RemoteDOMWindow.cpp"}
{"function": "location", "filename": "Document.cpp"}
{"function": "personalbar", "filename": "LocalDOMWindow.cpp"}
{"function": "personalbar", "filename": "RemoteDOMWindow.cpp"}
{"function": "readyState", "filename": "Document.cpp"}
{"function": "reload", "filename": "Location.cpp"}
{"function": "confirm", "filename": "LocalDOMWindow.cpp"}
{"function": "confirm", "filename": "RemoteDOMWindow.cpp"}
{"function": "preferredStyleSheetSet", "filename": "Document.cpp"}
{"function": "btoa", "filename": "DOMWindowBase64.cpp"}
{"function": "atob", "filename": "DOMWindowBase64.cpp"}
{"function": "toolbar", "filename": "LocalDOMWindow.cpp"}
{"function": "toolbar", "filename": "RemoteDOMWindow.cpp"}
{"function": "prompt", "filename": "LocalDOMWindow.cpp"}
{"function": "prompt", "filename": "RemoteDOMWindow.cpp"}
{"function": "scrollbars", "filename": "LocalDOMWindow.cpp"}
{"function": "scrollbars", "filename": "RemoteDOMWindow.cpp"}
{"function": "requestAnimationFrame", "filename": "LocalDOMWindow.cpp"}
{"function": "requestAnimationFrame", "filename": "RemoteDOMWindow.cpp"}
{"function": "lastModified", "filename": "Document.cpp"}
{"function": "parent", "filename": "DOMWindow.cpp"}
{"function": "close", "filename": "DOMWindow.cpp"}
{"function": "rect", "filename": "CanvasPathMethods.cpp"}
{"function": "arcTo", "filename": "CanvasPathMethods.cpp"}
{"function": "currentScriptForBinding", "filename": "Document.cpp"}
{"function": "moveTo", "filename": "CanvasPathMethods.cpp"}
{"function": "arc", "filename": "CanvasPathMethods.cpp"}
{"function": "images", "filename": "Document.cpp"}
{"function": "location", "filename": "DOMWindow.cpp"}
{"function": "closed", "filename": "DOMWindow.cpp"}
{"function": "activeElement", "filename": "Document.cpp"}
{"function": "createImageBitmap", "filename": "ImageBitmapFactories.cpp"}
{"function": "body", "filename": "Document.cpp"}
{"function": "links", "filename": "Document.cpp"}
{"function": "history", "filename": "LocalDOMWindow.cpp"}
{"function": "history", "filename": "RemoteDOMWindow.cpp"}
{"function": "focus", "filename": "DOMWindow.cpp"}
{"function": "document", "filename": "LocalDOMWindow.cpp"}
{"function": "document", "filename": "RemoteDOMWindow.cpp"}
{"function": "designMode", "filename": "Document.cpp"}
{"function": "blur", "filename": "LocalDOMWindow.cpp"}
{"function": "quadraticCurveTo", "filename": "CanvasPathMethods.cpp"}
{"function": "blur", "filename": "RemoteDOMWindow.cpp"}
{"function": "embeds", "filename": "Document.cpp"}
{"function": "head", "filename": "Document.cpp"}
{"function": "postMessage", "filename": "DOMWindow.cpp"}
{"function": "length", "filename": "DOMWindow.cpp"}
{"function": "stop", "filename": "LocalDOMWindow.cpp"}
{"function": "stop", "filename": "RemoteDOMWindow.cpp"}
{"function": "navigator", "filename": "LocalDOMWindow.cpp"}
{"function": "navigator", "filename": "RemoteDOMWindow.cpp"}
{"function": "open", "filename": "LocalDOMWindow.cpp"}
{"function": "selectedStyleSheetSet", "filename": "Document.cpp"}
{"function": "opener", "filename": "DOMWindow.cpp"}
{"function": "self", "filename": "DOMWindow.cpp"}
{"function": "top", "filename": "DOMWindow.cpp"}
{"function": "frameElement", "filename": "LocalDOMWindow.cpp"}
{"function": "lineTo", "filename": "CanvasPathMethods.cpp"}
{"function": "dir", "filename": "Document.cpp"}
{"function": "name", "filename": "LocalDOMWindow.cpp"}
{"function": "name", "filename": "RemoteDOMWindow.cpp"}
{"function": "bezierCurveTo", "filename": "CanvasPathMethods.cpp"}
{"function": "closePath", "filename": "CanvasPathMethods.cpp"}
{"function": "innerWidth", "filename": "RemoteDOMWindow.cpp"}
{"function": "innerWidth", "filename": "LocalDOMWindow.cpp"}
{"function": "MediaQueryList", "filename": "RemoteDOMWindow.cpp"}
{"function": "MediaQueryList", "filename": "LocalDOMWindow.cpp"}
{"function": "moveBy", "filename": "RemoteDOMWindow.cpp"}
{"function": "moveBy", "filename": "LocalDOMWindow.cpp"}
{"function": "resizeTo", "filename": "RemoteDOMWindow.cpp"}
{"function": "resizeTo", "filename": "LocalDOMWindow.cpp"}
{"function": "scrollBy", "filename": "RemoteDOMWindow.cpp"}
{"function": "scrollBy", "filename": "LocalDOMWindow.cpp"}
{"function": "resizeBy", "filename": "RemoteDOMWindow.cpp"}
{"function": "resizeBy", "filename": "LocalDOMWindow.cpp"}
{"function": "screenY", "filename": "RemoteDOMWindow.cpp"}
{"function": "screenY", "filename": "LocalDOMWindow.cpp"}
{"function": "outerWidth", "filename": "RemoteDOMWindow.cpp"}
{"function": "outerWidth", "filename": "LocalDOMWindow.cpp"}
{"function": "screenX", "filename": "RemoteDOMWindow.cpp"}
{"function": "screenX", "filename": "LocalDOMWindow.cpp"}
{"function": "scrollX", "filename": "RemoteDOMWindow.cpp"}
{"function": "scrollX", "filename": "LocalDOMWindow.cpp"}
{"function": "moveTo", "filename": "RemoteDOMWindow.cpp"}
{"function": "moveTo", "filename": "LocalDOMWindow.cpp"}
{"function": "scrollY", "filename": "RemoteDOMWindow.cpp"}
{"function": "scrollY", "filename": "LocalDOMWindow.cpp"}
{"function": "devicePixelRatio", "filename": "RemoteDOMWindow.cpp"}
{"function": "devicePixelRatio", "filename": "LocalDOMWindow.cpp"}
{"function": "innerHeight", "filename": "RemoteDOMWindow.cpp"}
{"function": "innerHeight", "filename": "LocalDOMWindow.cpp"}
{"function": "screen", "filename": "RemoteDOMWindow.cpp"}
{"function": "screen", "filename": "LocalDOMWindow.cpp"}
{"function": "outerHeight", "filename": "RemoteDOMWindow.cpp"}
{"function": "outerHeight", "filename": "LocalDOMWindow.cpp"}
{"function": "scrollTo", "filename": "RemoteDOMWindow.cpp"}
{"function": "scrollTo", "filename": "LocalDOMWindow.cpp"}
{"function": "colorDepth", "filename": "Screen.cpp"}
{"function": "availWidth", "filename": "Screen.cpp"}
{"function": "availHeight", "filename": "Screen.cpp"}
{"function": "width", "filename": "Screen.cpp"}
{"function": "height", "filename": "Screen.cpp"}
{"function": "pixelDepth", "filename": "Screen.cpp"}
{"function": "timelineCallback", "filename": "v8-console.cc"}
{"function": "logCallback", "filename": "v8-console.cc"}
{"function": "groupEndCallback", "filename": "v8-console.cc"}
{"function": "tableCallback", "filename": "v8-console.cc"}
{"function": "markTimelineCallback", "filename": "v8-console.cc"}
{"function": "assertCallback", "filename": "v8-console.cc"}
{"function": "profileEndCallback", "filename": "v8-console.cc"}
{"function": "groupCollapsedCallback", "filename": "v8-console.cc"}
{"function": "clearCallback", "filename": "v8-console.cc"}
{"function": "dirxmlCallback", "filename": "v8-console.cc"}
{"function": "timeEndCallback", "filename": "v8-console.cc"}
{"function": "errorCallback", "filename": "v8-console.cc"}
{"function": "profileCallback", "filename": "v8-console.cc"}
{"function": "warnCallback", "filename": "v8-console.cc"}
{"function": "traceCallback", "filename": "v8-console.cc"}
{"function": "infoCallback", "filename": "v8-console.cc"}
{"function": "countCallback", "filename": "v8-console.cc"}
{"function": "timeStampCallback", "filename": "v8-console.cc"}
{"function": "geolocation", "filename": "NavigatorGeolocation.cpp"}
{"function": "watchPosition", "filename": "Geolocation.cpp"}
{"function": "getCurrentPosition", "filename": "Geolocation.cpp"}
{"function": "clearWatch", "filename": "Geolocation.cpp"}
{"function": "scripts", "filename": "Document.cpp"}
{"function": "contentType", "filename": "Document.cpp"}
{"function": "compatMode", "filename": "Document.cpp"}
{"function": "close", "filename": "Document.cpp"}
{"function": "getReceivers", "filename": "peerconnection.cc"}
{"function": "getSenders", "filename": "peerconnection.cc"}
{"function": "removeTrack", "filename": "peerconnection.cc"}
{"function": "addTrack", "filename": "MediaStream.cpp"}
{"function": "createDataChannel", "filename": "RTCPeerConnection.cpp"}
{"function": "updateIce", "filename": "RTCPeerConnection.cpp"}
{"function": "addStream", "filename": "RTCPeerConnection.cpp"}
{"function": "createOffer", "filename": "RTCPeerConnection.cpp"}
{"function": "getStats", "filename": "RTCPeerConnection.cpp"}
{"function": "getStreamById", "filename": "RTCPeerConnection.cpp"}
{"function": "generateCertificate", "filename": "RTCPeerConnection.cpp"}
{"function": "createAnswer", "filename": "RTCPeerConnection.cpp"}
{"function": "removeStream", "filename": "RTCPeerConnection.cpp"}
{"function": "addIceCandidate", "filename": "RTCPeerConnection.cpp"}
{"function": "getRemoteStreams", "filename": "RTCPeerConnection.cpp"}
{"function": "getLocalStreams", "filename": "RTCPeerConnection.cpp"}
{"function": "setLocalDescription", "filename": "RTCPeerConnection.cpp"}
{"function": "setRemoteDescription", "filename": "RTCPeerConnection.cpp"}
{"function": "close", "filename": "RTCPeerConnection.cpp"}
{"function": "item", "filename": "CSSValueList.h"}
{"function": "getFloatValue", "filename": "CSSPrimitiveValue.h"}
{"function": "getComputedStyle", "filename": "LocalDOMWindow.cpp"}
{"function": "getComputedStyle", "filename": "RemoteDOMWindow.cpp"}
{"function": "doctype", "filename": "Document.h"}
{"function": "write", "filename": "Document.cpp"}
{"function": "open", "filename": "Document.cpp"}
{"function": "URL", "filename": "Document.h"}
{"function": "title", "filename": "Document.h"}
{"function": "domain", "filename": "Document.cpp"}
{"function": "cookie", "filename": "Document.cpp"}
{"function": "documentElement", "filename": "Document.h"}
{"function": "implementation", "filename": "Document.cpp"}
{"function": "writeln", "filename": "Document.cpp"}
{"function": "referrer", "filename": "Document.cpp"}
{"function": "forms", "filename": "Document.cpp"}
{"function": "domContentLoadedEventStart", "filename": "PerformanceTiming.cpp"}
{"function": "domLoading", "filename": "PerformanceTiming.cpp"}
{"function": "timing", "filename": "Performance.cpp"}
{"function": "unloadEventEnd", "filename": "PerformanceTiming.cpp"}
{"function": "navigation", "filename": "Performance.cpp"}
{"function": "connectStart", "filename": "PerformanceTiming.cpp"}
{"function": "loadEventStart", "filename": "PerformanceTiming.cpp"}
{"function": "connectEnd", "filename": "PerformanceTiming.cpp"}
{"function": "redirectEnd", "filename": "PerformanceTiming.cpp"}
{"function": "unloadEventStart", "filename": "PerformanceTiming.cpp"}
{"function": "navigationStart", "filename": "PerformanceTiming.cpp"}
{"function": "responseEnd", "filename": "PerformanceTiming.cpp"}
{"function": "domContentLoadedEventEnd", "filename": "PerformanceTiming.cpp"}
{"function": "responseStart", "filename": "PerformanceTiming.cpp"}
{"function": "redirectCount", "filename": "PerformanceNavigation.cpp"}
{"function": "domComplete", "filename": "PerformanceTiming.cpp"}
{"function": "domainLookupEnd", "filename": "PerformanceTiming.cpp"}
{"function": "domInteractive", "filename": "PerformanceTiming.cpp"}
{"function": "domainLookupStart", "filename": "PerformanceTiming.cpp"}
{"function": "redirectStart", "filename": "PerformanceTiming.cpp"}
{"function": "loadEventEnd", "filename": "PerformanceTiming.cpp"}
{"function": "type", "filename": "PerformanceNavigation.cpp"}
{"function": "fetchStart", "filename": "PerformanceTiming.cpp"}
{"function": "requestStart", "filename": "PerformanceTiming.cpp"}
{"function": "vibrate", "filename": "NavigatorVibration.cpp"}
{"function": "createObjectURL", "filename": "URLFileAPI.cpp"}
{"function": "revokeObjectURL", "filename": "URLFileAPI.cpp"}
{"function": "querySelector", "filename": "ParentNode.h"}
{"function": "querySelectorAll", "filename": "ParentNode.h"}
{"function": "getItem", "filename": "SVGStringList.cpp"}
{"function": "appendItem", "filename": "SVGStringList.cpp"}
{"function": "removeItem", "filename": "SVGStringList.cpp"}
{"function": "insertItemBefore", "filename": "SVGStringList.cpp"}
{"function": "initialize", "filename": "SVGStringList.cpp"}
{"function": "replaceItem", "filename": "SVGStringList.cpp"}
{"function": "getBattery", "filename": "NavigatorBattery.cpp"}
{"function": "getSelection", "filename": "RemoteDOMWindow.cpp"}
{"function": "getSelection", "filename": "LocalDOMWindow.cpp"}
{"function": "queryCommandIndeterm", "filename": "Document.cpp"}
{"function": "execCommand", "filename": "Document.cpp"}
{"function": "queryCommandValue", "filename": "Document.cpp"}
{"function": "queryCommandEnabled", "filename": "Document.cpp"}
{"function": "queryCommandSupported", "filename": "Document.cpp"}
{"function": "queryCommandState", "filename": "Document.cpp"}
{"function": "hidden", "filename": "Document.cpp"}
{"function": "visibilityState", "filename": "Document.cpp"}
{"function": "sendBeacon", "filename": "NavigatorBeacon.cpp"}
{"function": "cancelAnimationFrame", "filename": "RemoteDOMWindow.cpp"}
{"function": "cancelAnimationFrame", "filename": "LocalDOMWindow.cpp"}
{"function": "stopLocalMediaStream", "filename": "MediaStreamCenter.cpp"}
{"function": "mediaDevices", "filename": "NavigatorUserMedia.cpp"}
{"function": "requestMediaKeySystemAccess", "filename": "NavigatorRequestMediaKeySystemAccess.cpp"}
{"function": "item", "filename": "ClientRectList.cpp"}
{"function": "requestFrame", "filename": "CanvasCaptureMediaStreamTrack.cpp"}
{"function": "getGamepads", "filename": "NavigatorGamepad.cpp"}
{"function": "doNotTrack", "filename": "NavigatorDoNotTrack.cpp"}
{"function": "suspendcontext", "filename": "AudioContext.cpp"}
{"function": "suspendcontext", "filename": "OfflineAudioContext.cpp"}
{"function": "setResourceTimingBufferSize", "filename": "PerformanceBase.cpp"}
{"function": "restore", "filename": "BaseRenderingContext2D.cpp"}
{"function": "setLineDash", "filename": "BaseRenderingContext2D.cpp"}
{"function": "createRadialGradient", "filename": "BaseRenderingContext2D.cpp"}
{"function": "getLineDash", "filename": "BaseRenderingContext2D.cpp"}
{"function": "createImageData", "filename": "BaseRenderingContext2D.cpp"}
{"function": "clip", "filename": "BaseRenderingContext2D.cpp"}
{"function": "getImageData", "filename": "BaseRenderingContext2D.cpp"}
{"function": "scale", "filename": "BaseRenderingContext2D.cpp"}
{"function": "setTransform", "filename": "BaseRenderingContext2D.cpp"}
{"function": "fillRect", "filename": "BaseRenderingContext2D.cpp"}
{"function": "rotate", "filename": "BaseRenderingContext2D.cpp"}
{"function": "transform", "filename": "BaseRenderingContext2D.cpp"}
{"function": "drawImage", "filename": "BaseRenderingContext2D.cpp"}
{"function": "strokeRect", "filename": "BaseRenderingContext2D.cpp"}
{"function": "stroke", "filename": "BaseRenderingContext2D.cpp"}
{"function": "createPattern", "filename": "BaseRenderingContext2D.cpp"}
{"function": "putImageData", "filename": "BaseRenderingContext2D.cpp"}
{"function": "beginPath", "filename": "BaseRenderingContext2D.cpp"}
{"function": "translate", "filename": "BaseRenderingContext2D.cpp"}
{"function": "resetTransform", "filename": "BaseRenderingContext2D.cpp"}
{"function": "fill", "filename": "BaseRenderingContext2D.cpp"}
{"function": "clearRect", "filename": "BaseRenderingContext2D.cpp"}
{"function": "save", "filename": "BaseRenderingContext2D.cpp"}
{"function": "createLinearGradient", "filename": "BaseRenderingContext2D.cpp"}
{"function": "clearResourceTimings", "filename": "PerformanceBase.cpp"}
{"function": "clearMeasures", "filename": "PerformanceBase.cpp"}
{"function": "clearMarks", "filename": "PerformanceBase.cpp"}
{"function": "mark", "filename": "PerformanceBase.cpp"}
{"function": "measure", "filename": "PerformanceBase.cpp"}
{"function": "getEntriesByName", "filename": "PerformanceBase.cpp"}
{"function": "getEntriesByType", "filename": "PerformanceBase.cpp"}
{"function": "getEntries", "filename": "PerformanceBase.cpp"}
{"function": "now", "filename": "PerformanceBase.cpp"}
{"function": "setStart", "filename": "Range.cpp"}
{"function": "setEnd", "filename": "Range.cpp"}
{"function": "terminate", "filename": "InProcessWorkerBase.cpp"}
{"function": "postMessage", "filename": "InProcessWorkerBase.cpp"}
{"function": "transformToFragment", "filename": "XSLTProcessor.cpp"}
{"function": "reset", "filename": "XSLTProcessor.cpp"}
{"function": "clearParameters", "filename": "XSLTProcessor.cpp"}
{"function": "setParameter", "filename": "XSLTProcessor.cpp"}
{"function": "releaseEvents", "filename": "HTMLDocument.cpp"}
{"function": "removeParameter", "filename": "XSLTProcessor.cpp"}
{"function": "captureEvents", "filename": "HTMLDocument.cpp"}
{"function": "getParameter", "filename": "XSLTProcessor.cpp"}
{"function": "transformToDocument", "filename": "XSLTProcessor.cpp"}
{"function": "importStylesheet", "filename": "XSLTProcessor.cpp"}
{"function": "uniform4fv", "filename": "WebGLRenderingContextBase.cpp"}
{"function": "activeTexture", "filename": "WebGLRenderingContextBase.cpp"}
{"function": "isRenderbuffer", "filename": "WebGLRenderingContextBase.cpp"}
{"function": "blendEquation", "filename": "WebGLRenderingContextBase.cpp"}
{"function": "blendEquationSeparate", "filename": "WebGLRenderingContextBase.cpp"}
{"function": "getError", "filename": "WebGLRenderingContextBase.cpp"}
{"function": "deleteBuffer", "filename": "WebGLRenderingContextBase.cpp"}
{"function": "getFramebufferAttachmentParameter", "filename": "WebGLRenderingContextBase.cpp"}
{"function": "getContextAttributes", "filename": "WebGLRenderingContextBase.cpp"}
{"function": "detachShader", "filename": "WebGLRenderingContextBase.cpp"}
{"function": "createShader", "filename": "WebGLRenderingContextBase.cpp"}
{"function": "blendFunc", "filename": "WebGLRenderingContextBase.cpp"}
{"function": "blendFuncSeparate", "filename": "WebGLRenderingContextBase.cpp"}
{"function": "deleteTexture", "filename": "WebGLRenderingContextBase.cpp"}
{"function": "checkFramebufferStatus", "filename": "WebGLRenderingContextBase.cpp"}
{"function": "blendColor", "filename": "WebGLRenderingContextBase.cpp"}
{"function": "useProgram", "filename": "WebGLRenderingContextBase.cpp"}
{"function": "getExtension", "filename": "WebGLRenderingContextBase.cpp"}
{"function": "shaderSource", "filename": "WebGLRenderingContextBase.cpp"}
{"function": "getShaderParameter", "filename": "WebGLRenderingContextBase.cpp"}
{"function": "getParameter", "filename": "WebGLRenderingContextBase.cpp"}
{"function": "deleteRenderbuffer", "filename": "WebGLRenderingContextBase.cpp"}
{"function": "uniform3iv", "filename": "WebGLRenderingContextBase.cpp"}
{"function": "texSubImage2D", "filename": "WebGLRenderingContextBase.cpp"}
{"function": "pixelStorei", "filename": "WebGLRenderingContextBase.cpp"}
{"function": "texParameteri", "filename": "WebGLRenderingContextBase.cpp"}
{"function": "uniform2fv", "filename": "WebGLRenderingContextBase.cpp"}
{"function": "cullFace", "filename": "WebGLRenderingContextBase.cpp"}
{"function": "copyTexSubImage2D", "filename": "WebGLRenderingContextBase.cpp"}
{"function": "depthFunc", "filename": "WebGLRenderingContextBase.cpp"}
{"function": "createProgram", "filename": "WebGLRenderingContextBase.cpp"}
{"function": "polygonOffset", "filename": "WebGLRenderingContextBase.cpp"}
{"function": "uniform2f", "filename": "WebGLRenderingContextBase.cpp"}
{"function": "createRenderbuffer", "filename": "WebGLRenderingContextBase.cpp"}
{"function": "vertexAttrib1fv", "filename": "WebGLRenderingContextBase.cpp"}
{"function": "getShaderPrecisionFormat", "filename": "WebGLRenderingContextBase.cpp"}
{"function": "clearDepth", "filename": "WebGLRenderingContextBase.cpp"}
{"function": "clearColor", "filename": "WebGLRenderingContextBase.cpp"}
{"function": "vertexAttrib2fv", "filename": "WebGLRenderingContextBase.cpp"}
{"function": "isContextLost", "filename": "WebGLRenderingContextBase.cpp"}
{"function": "stencilOp", "filename": "WebGLRenderingContextBase.cpp"}
{"function": "uniform2i", "filename": "WebGLRenderingContextBase.cpp"}
{"function": "uniform3f", "filename": "WebGLRenderingContextBase.cpp"}
{"function": "hint", "filename": "WebGLRenderingContextBase.cpp"}
{"function": "isShader", "filename": "WebGLRenderingContextBase.cpp"}
{"function": "createBuffer", "filename": "WebGLRenderingContextBase.cpp"}
{"function": "getAttachedShaders", "filename": "WebGLRenderingContextBase.cpp"}
{"function": "framebufferTexture2D", "filename": "WebGLRenderingContextBase.cpp"}
{"function": "deleteShader", "filename": "WebGLRenderingContextBase.cpp"}
{"function": "isProgram", "filename": "WebGLRenderingContextBase.cpp"}
{"function": "uniform1f", "filename": "WebGLRenderingContextBase.cpp"}
{"function": "clearStencil", "filename": "WebGLRenderingContextBase.cpp"}
{"function": "uniformMatrix4fv", "filename": "WebGLRenderingContextBase.cpp"}
{"function": "getShaderSource", "filename": "WebGLRenderingContextBase.cpp"}
{"function": "scissor", "filename": "WebGLRenderingContextBase.cpp"}
{"function": "getSupportedExtensions", "filename": "WebGLRenderingContextBase.cpp"}
{"function": "isTexture", "filename": "WebGLRenderingContextBase.cpp"}
{"function": "getRenderbufferParameter", "filename": "WebGLRenderingContextBase.cpp"}
{"function": "uniform4f", "filename": "WebGLRenderingContextBase.cpp"}
{"function": "uniform3i", "filename": "WebGLRenderingContextBase.cpp"}
{"function": "validateProgram", "filename": "WebGLRenderingContextBase.cpp"}
{"function": "depthMask", "filename": "WebGLRenderingContextBase.cpp"}
{"function": "viewport", "filename": "WebGLRenderingContextBase.cpp"}
{"function": "uniform1fv", "filename": "WebGLRenderingContextBase.cpp"}
{"function": "texParameterf", "filename": "WebGLRenderingContextBase.cpp"}
{"function": "uniform4iv", "filename": "WebGLRenderingContextBase.cpp"}
{"function": "getBufferParameter", "filename": "WebGLRenderingContextBase.cpp"}
{"function": "vertexAttribPointer", "filename": "WebGLRenderingContextBase.cpp"}
{"function": "bindBuffer", "filename": "WebGLRenderingContextBase.cpp"}
{"function": "finish", "filename": "WebGLRenderingContextBase.cpp"}
{"function": "bindRenderbuffer", "filename": "WebGLRenderingContextBase.cpp"}
{"function": "vertexAttrib4f", "filename": "WebGLRenderingContextBase.cpp"}
{"function": "vertexAttrib3f", "filename": "WebGLRenderingContextBase.cpp"}
{"function": "uniform3fv", "filename": "WebGLRenderingContextBase.cpp"}
{"function": "copyTexImage2D", "filename": "WebGLRenderingContextBase.cpp"}
{"function": "sampleCoverage", "filename": "WebGLRenderingContextBase.cpp"}
{"function": "flush", "filename": "WebGLRenderingContextBase.cpp"}
{"function": "lineWidth", "filename": "WebGLRenderingContextBase.cpp"}
{"function": "deleteProgram", "filename": "WebGLRenderingContextBase.cpp"}
{"function": "getUniform", "filename": "WebGLRenderingContextBase.cpp"}
{"function": "bufferData", "filename": "WebGLRenderingContextBase.cpp"}
{"function": "getAttribLocation", "filename": "WebGLRenderingContextBase.cpp"}
{"function": "isFramebuffer", "filename": "WebGLRenderingContextBase.cpp"}
{"function": "bufferSubData", "filename": "WebGLRenderingContextBase.cpp"}
{"function": "uniform2iv", "filename": "WebGLRenderingContextBase.cpp"}
{"function": "vertexAttrib2f", "filename": "WebGLRenderingContextBase.cpp"}
{"function": "stencilFuncSeparate", "filename": "WebGLRenderingContextBase.cpp"}
{"function": "getActiveUniform", "filename": "WebGLRenderingContextBase.cpp"}
{"function": "getVertexAttrib", "filename": "WebGLRenderingContextBase.cpp"}
{"function": "readPixels", "filename": "WebGLRenderingContextBase.cpp"}
{"function": "frontFace", "filename": "WebGLRenderingContextBase.cpp"}
{"function": "vertexAttrib4fv", "filename": "WebGLRenderingContextBase.cpp"}
{"function": "compressedTexImage2D", "filename": "WebGLRenderingContextBase.cpp"}
{"function": "deleteFramebuffer", "filename": "WebGLRenderingContextBase.cpp"}
{"function": "enable", "filename": "WebGLRenderingContextBase.cpp"}
{"function": "bindFramebuffer", "filename": "WebGLRenderingContextBase.cpp"}
{"function": "texImage2D", "filename": "WebGLRenderingContextBase.cpp"}
{"function": "isEnabled", "filename": "WebGLRenderingContextBase.cpp"}
{"function": "framebufferRenderbuffer", "filename": "WebGLRenderingContextBase.cpp"}
{"function": "uniform4i", "filename": "WebGLRenderingContextBase.cpp"}
{"function": "colorMask", "filename": "WebGLRenderingContextBase.cpp"}
{"function": "uniform1i", "filename": "WebGLRenderingContextBase.cpp"}
{"function": "enableVertexAttribArray", "filename": "WebGLRenderingContextBase.cpp"}
{"function": "drawArrays", "filename": "WebGLRenderingContextBase.cpp"}
{"function": "isBuffer", "filename": "WebGLRenderingContextBase.cpp"}
{"function": "bindTexture", "filename": "WebGLRenderingContextBase.cpp"}
{"function": "getVertexAttribOffset", "filename": "WebGLRenderingContextBase.cpp"}
{"function": "compressedTexSubImage2D", "filename": "WebGLRenderingContextBase.cpp"}
{"function": "depthRange", "filename": "WebGLRenderingContextBase.cpp"}
{"function": "createTexture", "filename": "WebGLRenderingContextBase.cpp"}
{"function": "disableVertexAttribArray", "filename": "WebGLRenderingContextBase.cpp"}
{"function": "stencilMask", "filename": "WebGLRenderingContextBase.cpp"}
{"function": "uniform1iv", "filename": "WebGLRenderingContextBase.cpp"}
{"function": "generateMipmap", "filename": "WebGLRenderingContextBase.cpp"}
{"function": "getTexParameter", "filename": "WebGLRenderingContextBase.cpp"}
{"function": "attachShader", "filename": "WebGLRenderingContextBase.cpp"}
{"function": "getUniformLocation", "filename": "WebGLRenderingContextBase.cpp"}
{"function": "drawElements", "filename": "WebGLRenderingContextBase.cpp"}
{"function": "linkProgram", "filename": "WebGLRenderingContextBase.cpp"}
{"function": "vertexAttrib1f", "filename": "WebGLRenderingContextBase.cpp"}
{"function": "disable", "filename": "WebGLRenderingContextBase.cpp"}
{"function": "stencilMaskSeparate", "filename": "WebGLRenderingContextBase.cpp"}
{"function": "getShaderInfoLog", "filename": "WebGLRenderingContextBase.cpp"}
{"function": "clear", "filename": "WebGLRenderingContextBase.cpp"}
{"function": "uniformMatrix3fv", "filename": "WebGLRenderingContextBase.cpp"}
{"function": "stencilOpSeparate", "filename": "WebGLRenderingContextBase.cpp"}
{"function": "getProgramInfoLog", "filename": "WebGLRenderingContextBase.cpp"}
{"function": "getActiveAttrib", "filename": "WebGLRenderingContextBase.cpp"}
{"function": "getProgramParameter", "filename": "WebGLRenderingContextBase.cpp"}
{"function": "compileShader", "filename": "WebGLRenderingContextBase.cpp"}
{"function": "uniformMatrix2fv", "filename": "WebGLRenderingContextBase.cpp"}
{"function": "bindAttribLocation", "filename": "WebGLRenderingContextBase.cpp"}
{"function": "vertexAttrib3fv", "filename": "WebGLRenderingContextBase.cpp"}
{"function": "stencilFunc", "filename": "WebGLRenderingContextBase.cpp"}
{"function": "renderbufferStorage", "filename": "WebGLRenderingContextBase.cpp"}
{"function": "createFramebuffer", "filename": "WebGLRenderingContextBase.cpp"}
{"function": "getFrequencyResponse", "filename": "BiquadFilterNode.cpp"}
{"function": "item", "filename": "DOMTokenList.cpp"}
{"function": "end", "filename": "TimeRanges.cpp"}
{"function": "replaceData", "filename": "CharacterData.cpp"}
{"function": "clear", "filename": "HTMLDocument.cpp"}
{"function": "suspend", "filename": "OfflineAudioContext.cpp"}
{"function": "getElementsByClassName", "filename": "Element.cpp"}
{"function": "remove", "filename": "DOMTokenList.cpp"}
{"function": "setOrientation", "filename": "AudioListener.cpp"}
{"function": "resume", "filename": "BaseAudioContext.cpp"}
{"function": "createWaveShaper", "filename": "BaseAudioContext.cpp"}
{"function": "getChannelData", "filename": "AudioBuffer.cpp"}
{"function": "disconnect", "filename": "AudioNode.cpp"}
{"function": "append", "filename": "Headers.cpp"}
{"function": "start", "filename": "OscillatorNode.cpp"}
{"function": "substringData", "filename": "CharacterData.cpp"}
{"function": "getByteFrequencyData", "filename": "AnalyserNode.cpp"}
{"function": "set", "filename": "Headers.cpp"}
{"function": "createChannelSplitter", "filename": "BaseAudioContext.cpp"}
{"function": "getFloatTimeDomainData", "filename": "AnalyserNode.cpp"}
{"function": "toggle", "filename": "DOMTokenList.cpp"}
{"function": "createMediaElementSource", "filename": "BaseAudioContext.cpp"}
{"function": "createGain", "filename": "BaseAudioContext.cpp"}
{"function": "open", "filename": "XMLHttpRequest.cpp"}
{"function": "setPosition", "filename": "AudioListener.cpp"}
{"function": "clone", "filename": "Response.cpp"}
{"function": "createHTMLDocument", "filename": "DOMImplementation.cpp"}
{"function": "createMediaStreamSource", "filename": "BaseAudioContext.cpp"}
{"function": "namedItem", "filename": "HTMLAllCollection.cpp"}
{"function": "stop", "filename": "OscillatorNode.cpp"}
{"function": "overrideMimeType", "filename": "XMLHttpRequest.cpp"}
{"function": "copyToChannel", "filename": "AudioBuffer.cpp"}
{"function": "exponentialRampToValueAtTime", "filename": "AudioParam.cpp"}
{"function": "insertData", "filename": "CharacterData.cpp"}
{"function": "toDataURL", "filename": "HTMLCanvasElement.cpp"}
{"function": "close", "filename": "AudioContext.cpp"}
{"function": "appendData", "filename": "CharacterData.cpp"}
{"function": "cancelScheduledValues", "filename": "AudioParam.cpp"}
{"function": "has", "filename": "Headers.cpp"}
{"function": "getAllResponseHeaders", "filename": "XMLHttpRequest.cpp"}
{"function": "decode", "filename": "TextDecoder.cpp"}
{"function": "setValueAtTime", "filename": "AudioParam.cpp"}
{"function": "createStereoPanner", "filename": "BaseAudioContext.cpp"}
{"function": "getByteTimeDomainData", "filename": "AnalyserNode.cpp"}
{"function": "deleteData", "filename": "CharacterData.cpp"}
{"function": "toBlob", "filename": "HTMLCanvasElement.cpp"}
{"function": "getFloatFrequencyData", "filename": "AnalyserNode.cpp"}
{"function": "createAttribute", "filename": "Document.cpp"}
{"function": "connect", "filename": "AudioNode.cpp"}
{"function": "send", "filename": "XMLHttpRequest.cpp"}
{"function": "createBiquadFilter", "filename": "BaseAudioContext.cpp"}
{"function": "createScriptProcessor", "filename": "BaseAudioContext.cpp"}
{"function": "createProcessingInstruction", "filename": "Document.cpp"}
{"function": "contains", "filename": "DOMTokenList.cpp"}
{"function": "getResponseHeader", "filename": "XMLHttpRequest.cpp"}
{"function": "add", "filename": "DOMTokenList.cpp"}
{"function": "createChannelMerger", "filename": "BaseAudioContext.cpp"}
{"function": "setRequestHeader", "filename": "XMLHttpRequest.cpp"}
{"function": "setOrientation", "filename": "PannerNode.cpp"}
{"function": "createElement", "filename": "Document.cpp"}
{"function": "createBuffer", "filename": "BaseAudioContext.cpp"}
{"function": "setPeriodicWave", "filename": "OscillatorNode.cpp"}
{"function": "abort", "filename": "XMLHttpRequest.cpp"}
{"function": "linearRampToValueAtTime", "filename": "AudioParam.cpp"}
{"function": "start", "filename": "AudioBufferSourceNode.cpp"}
{"function": "createDelay", "filename": "BaseAudioContext.cpp"}
{"function": "setPosition", "filename": "PannerNode.cpp"}
{"function": "stop", "filename": "AudioBufferSourceNode.cpp"}
{"function": "startRendering", "filename": "OfflineAudioContext.cpp"}
{"function": "get", "filename": "Headers.cpp"}
{"function": "closest", "filename": "Element.cpp"}
{"function": "setValueCurveAtTime", "filename": "AudioParam.cpp"}
{"function": "createPeriodicWave", "filename": "BaseAudioContext.cpp"}
{"function": "createDynamicsCompressor", "filename": "BaseAudioContext.cpp"}
{"function": "error", "filename": "Response.cpp"}
{"function": "decodeAudioData", "filename": "BaseAudioContext.cpp"}
{"function": "matches", "filename": "Element.cpp"}
{"function": "copyFromChannel", "filename": "AudioBuffer.cpp"}
{"function": "createPanner", "filename": "BaseAudioContext.cpp"}
{"function": "createMediaStreamDestination", "filename": "BaseAudioContext.cpp"}
{"function": "start", "filename": "TimeRanges.cpp"}
{"function": "createConvolver", "filename": "BaseAudioContext.cpp"}
{"function": "getElementsByClassName", "filename": "Document.cpp"}
{"function": "redirect", "filename": "Response.cpp"}
{"function": "item", "filename": "HTMLAllCollection.cpp"}
{"function": "createOscillator", "filename": "BaseAudioContext.cpp"}
{"function": "getAll", "filename": "Headers.cpp"}
{"function": "createAnalyser", "filename": "BaseAudioContext.cpp"}
{"function": "createBufferSource", "filename": "BaseAudioContext.cpp"}
{"function": "clone", "filename": "Request.cpp"}
{"function": "delete", "filename": "Headers.cpp"}
{"function": "encode", "filename": "TextEncoder.cpp"}
{"function": "getItem", "filename": "SVGNumberListTearOff.cpp"}
{"function": "nextSibling", "filename": "TreeWalker.cpp"}
{"function": "checkValidity", "filename": "HTMLTextAreaElement.cpp"}
{"function": "abort", "filename": "FileReader.cpp"}
{"function": "verify", "filename": "SubtleCrypto.cpp"}
{"function": "collapse", "filename": "DOMSelection.cpp"}
{"function": "replaceItem", "filename": "SVGPointListTearOff.cpp"}
{"function": "addCue", "filename": "TextTrack.cpp"}
{"function": "cloneContents", "filename": "Range.cpp"}
{"function": "getAttributeNS", "filename": "Element.cpp"}
{"function": "intersectsNode", "filename": "Range.cpp"}
{"function": "skewX", "filename": "DOMMatrixReadOnly.cpp"}
{"function": "insertRow", "filename": "HTMLTableSectionElement.cpp"}
{"function": "close", "filename": "RTCDataChannel.cpp"}
{"function": "compareBoundaryPoints", "filename": "Range.cpp"}
{"function": "dispatchEvent", "filename": "EventTarget.cpp"}
{"function": "openCursor", "filename": "IDBIndex.cpp"}
{"function": "setCustomValidity", "filename": "HTMLFieldSetElement.cpp"}
{"function": "getCurrentTime", "filename": "SVGAnimationElement.cpp"}
{"function": "evaluate", "filename": "XPathEvaluator.cpp"}
{"function": "getPropertyValue", "filename": "CSSStyleDeclaration.cpp"}
{"function": "deleteTHead", "filename": "HTMLTableElement.cpp"}
{"function": "selectNodeContents", "filename": "Range.cpp"}
{"function": "appendMedium", "filename": "MediaList.cpp"}
{"function": "deleteMedium", "filename": "MediaList.cpp"}
{"function": "endElementAt", "filename": "SVGAnimationElement.cpp"}
{"function": "close", "filename": "MessagePort.cpp"}
{"function": "generateRequest", "filename": "MediaKeySession.cpp"}
{"function": "getAttribute", "filename": "Element.cpp"}
{"function": "createSVGTransformFromMatrix", "filename": "SVGSVGElement.cpp"}
{"function": "item", "filename": "FileList.cpp"}
{"function": "removeProperty", "filename": "CSSStyleDeclaration.cpp"}
{"function": "play", "filename": "HTMLMediaElement.cpp"}
{"function": "createAttributeNS", "filename": "Document.cpp"}
{"function": "deleteContents", "filename": "Range.cpp"}
{"function": "put", "filename": "IDBObjectStore.cpp"}
{"function": "getBoundingClientRect", "filename": "Range.cpp"}
{"function": "getTracks", "filename": "MediaStream.cpp"}
{"function": "setNamedItemNS", "filename": "NamedNodeMap.cpp"}
{"function": "firstChild", "filename": "TreeWalker.cpp"}
{"function": "match", "filename": "Cache.cpp"}
{"function": "scaleNonUniform", "filename": "SVGMatrixTearOff.cpp"}
{"function": "upperBound", "filename": "IDBKeyRange.cpp"}
{"function": "append", "filename": "URLSearchParams.cpp"}
{"function": "checkValidity", "filename": "HTMLOutputElement.cpp"}
{"function": "createTHead", "filename": "HTMLTableElement.cpp"}
{"function": "requestPermission", "filename": "Notification.cpp"}
{"function": "AddSearchProvider", "filename": "External.cpp"}
{"function": "bound", "filename": "IDBKeyRange.cpp"}
{"function": "invertSelf", "filename": "DOMMatrix.cpp"}
{"function": "multiplySelf", "filename": "DOMMatrix.cpp"}
{"function": "set", "filename": "FormData.cpp"}
{"function": "delete", "filename": "IDBCursor.cpp"}
{"function": "createNodeIterator", "filename": "Document.cpp"}
{"function": "appendItem", "filename": "SVGNumberListTearOff.cpp"}
{"function": "deleteTFoot", "filename": "HTMLTableElement.cpp"}
{"function": "translate", "filename": "DOMMatrixReadOnly.cpp"}
{"function": "isTypeSupported", "filename": "MediaSource.cpp"}
{"function": "modify", "filename": "DOMSelection.cpp"}
{"function": "serializeToString", "filename": "XMLSerializer.cpp"}
{"function": "removeAttributeNode", "filename": "Element.cpp"}
{"function": "snapshotItem", "filename": "XPathResult.cpp"}
{"function": "createElementNS", "filename": "Document.cpp"}
{"function": "readAsDataURL", "filename": "FileReader.cpp"}
{"function": "reset", "filename": "HTMLFormElement.cpp"}
{"function": "previousSibling", "filename": "TreeWalker.cpp"}
{"function": "removeAttribute", "filename": "Element.cpp"}
{"function": "createDocument", "filename": "DOMImplementation.cpp"}
{"function": "send", "filename": "RTCDataChannel.cpp"}
{"function": "getRandomValues", "filename": "Crypto.cpp"}
{"function": "addTextTrack", "filename": "HTMLMediaElement.cpp"}
{"function": "pause", "filename": "HTMLMediaElement.cpp"}
{"function": "insertItemBefore", "filename": "SVGNumberListTearOff.cpp"}
{"function": "setTransform", "filename": "CanvasPattern.cpp"}
{"function": "objectStore", "filename": "IDBTransaction.cpp"}
{"function": "openCursor", "filename": "IDBObjectStore.cpp"}
{"function": "get", "filename": "IDBObjectStore.cpp"}
{"function": "removeSourceBuffer", "filename": "MediaSource.cpp"}
{"function": "removeNamedItem", "filename": "NamedNodeMap.cpp"}
{"function": "createCDATASection", "filename": "Document.cpp"}
{"function": "namedItem", "filename": "DOMPluginArray.cpp"}
{"function": "setCustomValidity", "filename": "HTMLObjectElement.cpp"}
{"function": "namedItem", "filename": "DOMPlugin.cpp"}
{"function": "removeItem", "filename": "SVGLengthListTearOff.cpp"}
{"function": "initEvent", "filename": "Event.cpp"}
{"function": "deleteRule", "filename": "CSSStyleSheet.cpp"}
{"function": "contains", "filename": "Node.cpp"}
{"function": "load", "filename": "FontFaceSet.cpp"}
{"function": "createMediaKeys", "filename": "MediaKeySystemAccess.cpp"}
{"function": "setTranslate", "filename": "SVGTransformTearOff.cpp"}
{"function": "hasFeature", "filename": "DOMImplementation.cpp"}
{"function": "focus", "filename": "HTMLElement.cpp"}
{"function": "rotateFromVector", "filename": "SVGMatrixTearOff.cpp"}
{"function": "detach", "filename": "NodeIterator.cpp"}
{"function": "deleteIndex", "filename": "IDBObjectStore.cpp"}
{"function": "getConfiguration", "filename": "MediaKeySystemAccess.cpp"}
{"function": "toFloat64Array", "filename": "DOMMatrixReadOnly.cpp"}
{"function": "getUserMedia", "filename": "MediaDevices.cpp"}
{"function": "getStartPositionOfChar", "filename": "SVGTextContentElement.cpp"}
{"function": "item", "filename": "CSSRuleList.cpp"}
{"function": "lowerBound", "filename": "IDBKeyRange.cpp"}
{"function": "consolidate", "filename": "SVGTransformListTearOff.cpp"}
{"function": "setSkewX", "filename": "SVGTransformTearOff.cpp"}
{"function": "get", "filename": "IDBIndex.cpp"}
{"function": "rotateFromVector", "filename": "DOMMatrixReadOnly.cpp"}
{"function": "skewY", "filename": "DOMMatrixReadOnly.cpp"}
{"function": "namedItem", "filename": "HTMLCollection.cpp"}
{"function": "checkValidity", "filename": "HTMLSelectElement.cpp"}
{"function": "appendItem", "filename": "SVGPointListTearOff.cpp"}
{"function": "isEqualNode", "filename": "Node.cpp"}
{"function": "setEndBefore", "filename": "Range.cpp"}
{"function": "createSession", "filename": "MediaKeys.cpp"}
{"function": "appendItem", "filename": "SVGStringListTearOff.cpp"}
{"function": "forceRedraw", "filename": "SVGSVGElement.cpp"}
{"function": "submit", "filename": "HTMLFormElement.cpp"}
{"function": "checkValidity", "filename": "HTMLObjectElement.cpp"}
{"function": "removeItem", "filename": "Storage.cpp"}
{"function": "removeCue", "filename": "TextTrack.cpp"}
{"function": "getItem", "filename": "SVGStringListTearOff.cpp"}
{"function": "setScale", "filename": "SVGTransformTearOff.cpp"}
{"function": "appendBuffer", "filename": "SourceBuffer.cpp"}
{"function": "delete", "filename": "FormData.cpp"}
{"function": "count", "filename": "IDBObjectStore.cpp"}
{"function": "toFloat32Array", "filename": "DOMMatrixReadOnly.cpp"}
{"function": "hasAttributes", "filename": "Element.cpp"}
{"function": "flipX", "filename": "DOMMatrixReadOnly.cpp"}
{"function": "adoptNode", "filename": "Document.cpp"}
{"function": "selectNode", "filename": "Range.cpp"}
{"function": "checkValidity", "filename": "HTMLButtonElement.cpp"}
{"function": "selectSubString", "filename": "SVGTextContentElement.cpp"}
{"function": "getSimpleDuration", "filename": "SVGAnimationElement.cpp"}
{"function": "getNumberOfChars", "filename": "SVGTextContentElement.cpp"}
{"function": "createSVGTransformFromMatrix", "filename": "SVGTransformListTearOff.cpp"}
{"function": "getElementById", "filename": "SVGSVGElement.cpp"}
{"function": "checkValidity", "filename": "HTMLFieldSetElement.cpp"}
{"function": "createSVGLength", "filename": "SVGSVGElement.cpp"}
{"function": "start", "filename": "MediaRecorder.cpp"}
{"function": "exportKey", "filename": "SubtleCrypto.cpp"}
{"function": "cloneRange", "filename": "Range.cpp"}
{"function": "add", "filename": "Cache.cpp"}
{"function": "initialize", "filename": "SVGPointListTearOff.cpp"}
{"function": "transaction", "filename": "IDBDatabase.cpp"}
{"function": "createTextNode", "filename": "Document.cpp"}
{"function": "only", "filename": "IDBKeyRange.cpp"}
{"function": "click", "filename": "HTMLElement.cpp"}
{"function": "load", "filename": "HTMLMediaElement.cpp"}
{"function": "rotateSelf", "filename": "DOMMatrix.cpp"}
{"function": "item", "filename": "HTMLCollection.cpp"}
{"function": "delete", "filename": "Cache.cpp"}
{"function": "initMouseEvent", "filename": "MouseEvent.cpp"}
{"function": "item", "filename": "StyleSheetList.cpp"}
{"function": "addSourceBuffer", "filename": "MediaSource.cpp"}
{"function": "index", "filename": "IDBObjectStore.cpp"}
{"function": "item", "filename": "DOMPluginArray.cpp"}
{"function": "setEndAfter", "filename": "Range.cpp"}
{"function": "insertAdjacentHTML", "filename": "Element.cpp"}
{"function": "setCustomValidity", "filename": "HTMLSelectElement.cpp"}
{"function": "pushState", "filename": "History.cpp"}
{"function": "deleteFromDocument", "filename": "DOMSelection.cpp"}
{"function": "slice", "filename": "Blob.cpp"}
{"function": "refresh", "filename": "DOMPluginArray.cpp"}
{"function": "setRangeText", "filename": "HTMLInputElement.cpp"}
{"function": "insertItemBefore", "filename": "SVGPointListTearOff.cpp"}
{"function": "getSubStringLength", "filename": "SVGTextContentElement.cpp"}
{"function": "lastChild", "filename": "TreeWalker.cpp"}
{"function": "skewYSelf", "filename": "DOMMatrix.cpp"}
{"function": "containsNode", "filename": "DOMSelection.cpp"}
{"function": "removeItem", "filename": "SVGNumberListTearOff.cpp"}
{"function": "suspendRedraw", "filename": "SVGSVGElement.cpp"}
{"function": "disconnect", "filename": "MutationObserver.cpp"}
{"function": "setSelectionRange", "filename": "HTMLTextAreaElement.cpp"}
{"function": "has", "filename": "FormData.cpp"}
{"function": "postMessage", "filename": "BroadcastChannel.cpp"}
{"function": "rotate", "filename": "SVGMatrixTearOff.cpp"}
{"function": "surroundContents", "filename": "Range.cpp"}
{"function": "close", "filename": "DOMWebSocket.cpp"}
{"function": "createSVGPoint", "filename": "SVGSVGElement.cpp"}
{"function": "appendItem", "filename": "SVGTransformListTearOff.cpp"}
{"function": "keys", "filename": "CacheStorage.cpp"}
{"function": "multiply", "filename": "SVGMatrixTearOff.cpp"}
{"function": "clear", "filename": "SVGStringListTearOff.cpp"}
{"function": "setAttribute", "filename": "Element.cpp"}
{"function": "checkValidity", "filename": "HTMLInputElement.cpp"}
{"function": "createIndex", "filename": "IDBObjectStore.cpp"}
{"function": "has", "filename": "CacheStorage.cpp"}
{"function": "setCustomValidity", "filename": "HTMLOutputElement.cpp"}
{"function": "removeChild", "filename": "Node.cpp"}
{"function": "clear", "filename": "SVGTransformListTearOff.cpp"}
{"function": "remove", "filename": "MediaKeySession.cpp"}
{"function": "getPropertyPriority", "filename": "CSSStyleDeclaration.cpp"}
{"function": "insertItemBefore", "filename": "SVGLengthListTearOff.cpp"}
{"function": "stepDown", "filename": "HTMLInputElement.cpp"}
{"function": "addListener", "filename": "MediaQueryList.cpp"}
{"function": "remove", "filename": "SourceBuffer.cpp"}
{"function": "replaceItem", "filename": "SVGNumberListTearOff.cpp"}
{"function": "advance", "filename": "IDBCursor.cpp"}
{"function": "unlock", "filename": "ScreenOrientation.cpp"}
{"function": "supports", "filename": "DOMWindowCSS.cpp"}
{"function": "isDefaultNamespace", "filename": "Node.cpp"}
{"function": "load", "filename": "FontFace.cpp"}
{"function": "skewXSelf", "filename": "DOMMatrix.cpp"}
{"function": "lookupNamespaceURI", "filename": "Node.cpp"}
{"function": "removeItem", "filename": "SVGStringListTearOff.cpp"}
{"function": "drawFocusIfNeeded", "filename": "CanvasRenderingContext2D.cpp"}
{"function": "get", "filename": "FormData.cpp"}
{"function": "initDeviceMotionEvent", "filename": "DeviceMotionEvent.cpp"}
{"function": "getBoundingClientRect", "filename": "Element.cpp"}
{"function": "replaceItem", "filename": "SVGLengthListTearOff.cpp"}
{"function": "setDragImage", "filename": "DataTransfer.cpp"}
{"function": "readAsText", "filename": "FileReader.cpp"}
{"function": "getData", "filename": "DataTransfer.cpp"}
{"function": "stop", "filename": "MediaStreamTrack.cpp"}
{"function": "replaceItem", "filename": "SVGTransformListTearOff.cpp"}
{"function": "wrapKey", "filename": "SubtleCrypto.cpp"}
{"function": "setAttributeNS", "filename": "Element.cpp"}
{"function": "normalize", "filename": "Node.cpp"}
{"function": "initialize", "filename": "SVGLengthListTearOff.cpp"}
{"function": "add", "filename": "IDBObjectStore.cpp"}
{"function": "createSVGNumber", "filename": "SVGSVGElement.cpp"}
{"function": "cmp", "filename": "IDBFactory.cpp"}
{"function": "stopImmediatePropagation", "filename": "Event.cpp"}
{"function": "translateSelf", "filename": "DOMMatrix.cpp"}
{"function": "getItem", "filename": "SVGPointListTearOff.cpp"}
{"function": "getExtentOfChar", "filename": "SVGTextContentElement.cpp"}
{"function": "add", "filename": "HTMLSelectElement.cpp"}
{"function": "initMutationEvent", "filename": "MutationEvent.cpp"}
{"function": "stop", "filename": "MediaRecorder.cpp"}
{"function": "getStartTime", "filename": "SVGAnimationElement.cpp"}
{"function": "importNode", "filename": "Document.cpp"}
{"function": "checkValidity", "filename": "HTMLFormElement.cpp"}
{"function": "close", "filename": "IDBDatabase.cpp"}
{"function": "previousNode", "filename": "NodeIterator.cpp"}
{"function": "takeRecords", "filename": "MutationObserver.cpp"}
{"function": "collapseToStart", "filename": "DOMSelection.cpp"}
{"function": "setCustomValidity", "filename": "HTMLButtonElement.cpp"}
{"function": "removeItem", "filename": "SVGTransformListTearOff.cpp"}
{"function": "createCaption", "filename": "HTMLTableElement.cpp"}
{"function": "setData", "filename": "DataTransfer.cpp"}
{"function": "scale", "filename": "SVGMatrixTearOff.cpp"}
{"function": "initStorageEvent", "filename": "StorageEvent.cpp"}
{"function": "lookupPrefix", "filename": "Node.cpp"}
{"function": "nextNode", "filename": "NodeIterator.cpp"}
{"function": "addRange", "filename": "DOMSelection.cpp"}
{"function": "setStdDeviation", "filename": "SVGFEGaussianBlurElement.cpp"}
{"function": "getElementsByTagNameNS", "filename": "Element.cpp"}
{"function": "setRangeText", "filename": "HTMLTextAreaElement.cpp"}
{"function": "select", "filename": "HTMLTextAreaElement.cpp"}
{"function": "insertCell", "filename": "HTMLTableRowElement.cpp"}
{"function": "setCustomValidity", "filename": "HTMLTextAreaElement.cpp"}
{"function": "createTBody", "filename": "HTMLTableElement.cpp"}
{"function": "item", "filename": "DOMMimeTypeArray.cpp"}
{"function": "blur", "filename": "HTMLElement.cpp"}
{"function": "createObjectStore", "filename": "IDBDatabase.cpp"}
{"function": "getSVGDocument", "filename": "HTMLEmbedElement.cpp"}
{"function": "setStartAfter", "filename": "Range.cpp"}
{"function": "scrollTo", "filename": "Element.cpp"}
{"function": "iterateNext", "filename": "XPathResult.cpp"}
{"function": "previousNode", "filename": "TreeWalker.cpp"}
{"function": "close", "filename": "BroadcastChannel.cpp"}
{"function": "preMultiplySelf", "filename": "DOMMatrix.cpp"}
{"function": "getElementsByTagName", "filename": "Document.cpp"}
{"function": "removeAttributeNS", "filename": "Element.cpp"}
{"function": "strokeText", "filename": "CanvasRenderingContext2D.cpp"}
{"function": "replaceChild", "filename": "Node.cpp"}
{"function": "contains", "filename": "DOMStringList.cpp"}
{"function": "getTrackById", "filename": "TextTrackList.cpp"}
{"function": "removeAllRanges", "filename": "DOMSelection.cpp"}
{"function": "initDeviceOrientationEvent", "filename": "DeviceOrientationEvent.cpp"}
{"function": "digest", "filename": "SubtleCrypto.cpp"}
{"function": "replaceItem", "filename": "SVGStringListTearOff.cpp"}
{"function": "setStartBefore", "filename": "Range.cpp"}
{"function": "getAll", "filename": "URLSearchParams.cpp"}
{"function": "comparePoint", "filename": "Range.cpp"}
{"function": "delete", "filename": "URLSearchParams.cpp"}
{"function": "removeNamedItemNS", "filename": "NamedNodeMap.cpp"}
{"function": "getBBox", "filename": "SVGGraphicsElement.cpp"}
{"function": "stopPropagation", "filename": "Event.cpp"}
{"function": "append", "filename": "FormData.cpp"}
{"function": "unwrapKey", "filename": "SubtleCrypto.cpp"}
{"function": "deleteRow", "filename": "HTMLTableSectionElement.cpp"}
{"function": "escape", "filename": "DOMWindowCSS.cpp"}
{"function": "stepUp", "filename": "HTMLInputElement.cpp"}
{"function": "has", "filename": "URLSearchParams.cpp"}
{"function": "createExpression", "filename": "XPathEvaluator.cpp"}
{"function": "observe", "filename": "MutationObserver.cpp"}
{"function": "scale3d", "filename": "DOMMatrixReadOnly.cpp"}
{"function": "removeEventListener", "filename": "EventTarget.cpp"}
{"function": "measureText", "filename": "CanvasRenderingContext2D.cpp"}
{"function": "sign", "filename": "SubtleCrypto.cpp"}
{"function": "unsuspendRedrawAll", "filename": "SVGSVGElement.cpp"}
{"function": "matrixTransform", "filename": "SVGPointTearOff.cpp"}
{"function": "getVideoTracks", "filename": "MediaStream.cpp"}
{"function": "initUIEvent", "filename": "UIEvent.cpp"}
{"function": "item", "filename": "NodeList.cpp"}
{"function": "getKey", "filename": "IDBIndex.cpp"}
{"function": "getElementsByTagNameNS", "filename": "Document.cpp"}
{"function": "close", "filename": "EventSource.cpp"}
{"function": "delete", "filename": "IDBObjectStore.cpp"}
{"function": "getAttributeNodeNS", "filename": "Element.cpp"}
{"function": "rotate", "filename": "DOMMatrixReadOnly.cpp"}
{"function": "forward", "filename": "History.cpp"}
{"function": "multiply", "filename": "DOMMatrixReadOnly.cpp"}
{"function": "namedItem", "filename": "HTMLSelectElement.cpp"}
{"function": "close", "filename": "Notification.cpp"}
{"function": "inverse", "filename": "SVGMatrixTearOff.cpp"}
{"function": "createSVGAngle", "filename": "SVGSVGElement.cpp"}
{"function": "translate", "filename": "SVGMatrixTearOff.cpp"}
{"function": "remove", "filename": "HTMLSelectElement.cpp"}
{"function": "abort", "filename": "SourceBuffer.cpp"}
{"function": "hasAttributeNS", "filename": "Element.cpp"}
{"function": "hasChildNodes", "filename": "Node.cpp"}
{"function": "scale", "filename": "DOMMatrixReadOnly.cpp"}
{"function": "newValueSpecifiedUnits", "filename": "SVGLengthTearOff.cpp"}
{"function": "pause", "filename": "MediaRecorder.cpp"}
{"function": "getRangeAt", "filename": "DOMSelection.cpp"}
{"function": "deleteObjectStore", "filename": "IDBDatabase.cpp"}
{"function": "getItem", "filename": "Storage.cpp"}
{"function": "convertToSpecifiedUnits", "filename": "SVGLengthTearOff.cpp"}
{"function": "setServerCertificate", "filename": "MediaKeys.cpp"}
{"function": "extend", "filename": "DOMSelection.cpp"}
{"function": "createRange", "filename": "Document.cpp"}
{"function": "resume", "filename": "MediaRecorder.cpp"}
{"function": "getNamedItemNS", "filename": "NamedNodeMap.cpp"}
{"function": "start", "filename": "MessagePort.cpp"}
{"function": "remove", "filename": "HTMLSelectElement.cpp"}
{"function": "openKeyCursor", "filename": "IDBIndex.cpp"}
{"function": "skewX", "filename": "SVGMatrixTearOff.cpp"}
{"function": "selectAllChildren", "filename": "DOMSelection.cpp"}
{"function": "setItem", "filename": "Storage.cpp"}
{"function": "setNamedItem", "filename": "NamedNodeMap.cpp"}
{"function": "extractContents", "filename": "Range.cpp"}
{"function": "isPointInStroke", "filename": "CanvasRenderingContext2D.cpp"}
{"function": "check", "filename": "FontFaceSet.cpp"}
{"function": "decrypt", "filename": "SubtleCrypto.cpp"}
{"function": "rotateAxisAngleSelf", "filename": "DOMMatrix.cpp"}
{"function": "initialize", "filename": "SVGStringListTearOff.cpp"}
{"function": "setCurrentTime", "filename": "SVGSVGElement.cpp"}
{"function": "hasAttribute", "filename": "Element.cpp"}
{"function": "namedItem", "filename": "DOMMimeTypeArray.cpp"}
{"function": "animationsPaused", "filename": "SVGSVGElement.cpp"}
{"function": "clear", "filename": "IDBObjectStore.cpp"}
{"function": "getAttributeNode", "filename": "Element.cpp"}
{"function": "setOrientToAuto", "filename": "SVGMarkerElement.cpp"}
{"function": "count", "filename": "IDBIndex.cpp"}
{"function": "update", "filename": "MediaKeySession.cpp"}
{"function": "unsuspendRedraw", "filename": "SVGSVGElement.cpp"}
{"function": "encrypt", "filename": "SubtleCrypto.cpp"}
{"function": "back", "filename": "History.cpp"}
{"function": "requestData", "filename": "MediaRecorder.cpp"}
{"function": "getSVGDocument", "filename": "HTMLObjectElement.cpp"}
{"function": "evaluate", "filename": "XPathExpression.cpp"}
{"function": "rotateFromVectorSelf", "filename": "DOMMatrix.cpp"}
{"function": "collapseToEnd", "filename": "DOMSelection.cpp"}
{"function": "insertItemBefore", "filename": "SVGTransformListTearOff.cpp"}
{"function": "getClientRects", "filename": "Element.cpp"}
{"function": "createTFoot", "filename": "HTMLTableElement.cpp"}
{"function": "nextNode", "filename": "TreeWalker.cpp"}
{"function": "createTreeWalker", "filename": "Document.cpp"}
{"function": "getCueById", "filename": "TextTrackCueList.cpp"}
{"function": "clear", "filename": "Storage.cpp"}
{"function": "deleteRow", "filename": "HTMLTableElement.cpp"}
{"function": "getItem", "filename": "SVGLengthListTearOff.cpp"}
{"function": "insertBefore", "filename": "Node.cpp"}
{"function": "update", "filename": "IDBCursor.cpp"}
{"function": "IsSearchProviderInstalled", "filename": "External.cpp"}
{"function": "deriveKey", "filename": "SubtleCrypto.cpp"}
{"function": "abort", "filename": "IDBTransaction.cpp"}
{"function": "getCueAsHTML", "filename": "VTTCue.cpp"}
{"function": "keys", "filename": "Cache.cpp"}
{"function": "getEndPositionOfChar", "filename": "SVGTextContentElement.cpp"}
{"function": "setProperty", "filename": "CSSStyleDeclaration.cpp"}
{"function": "addAll", "filename": "Cache.cpp"}
{"function": "createNSResolver", "filename": "XPathEvaluator.cpp"}
{"function": "deleteCell", "filename": "HTMLTableRowElement.cpp"}
{"function": "createSVGRect", "filename": "SVGSVGElement.cpp"}
{"function": "open", "filename": "CacheStorage.cpp"}
{"function": "continue", "filename": "IDBCursor.cpp"}
{"function": "getElementsByTagName", "filename": "Element.cpp"}
{"function": "endOfStream", "filename": "MediaSource.cpp"}
{"function": "beginElement", "filename": "SVGAnimationElement.cpp"}
{"function": "inverse", "filename": "DOMMatrixReadOnly.cpp"}
{"function": "matchAll", "filename": "Cache.cpp"}
{"function": "initialize", "filename": "SVGTransformListTearOff.cpp"}
{"function": "setSkewY", "filename": "SVGTransformTearOff.cpp"}
{"function": "convertToSpecifiedUnits", "filename": "SVGAngleTearOff.cpp"}
{"function": "getRotationOfChar", "filename": "SVGTextContentElement.cpp"}
{"function": "createSVGMatrix", "filename": "SVGSVGElement.cpp"}
{"function": "close", "filename": "MediaKeySession.cpp"}
{"function": "removeItem", "filename": "SVGPointListTearOff.cpp"}
{"function": "clear", "filename": "SVGLengthListTearOff.cpp"}
{"function": "load", "filename": "MediaKeySession.cpp"}
{"function": "createComment", "filename": "Document.cpp"}
{"function": "setMatrixValue", "filename": "DOMMatrix.cpp"}
{"function": "scrollBy", "filename": "Element.cpp"}
{"function": "match", "filename": "CacheStorage.cpp"}
{"function": "put", "filename": "Cache.cpp"}
{"function": "key", "filename": "Storage.cpp"}
{"function": "setStdDeviation", "filename": "SVGFEDropShadowElement.cpp"}
{"function": "rotateAxisAngle", "filename": "DOMMatrixReadOnly.cpp"}
{"function": "getScreenCTM", "filename": "SVGGraphicsElement.cpp"}
{"function": "addPath", "filename": "Path2D.cpp"}
{"function": "isPointInPath", "filename": "CanvasRenderingContext2D.cpp"}
{"function": "parentNode", "filename": "TreeWalker.cpp"}
{"function": "clearData", "filename": "DataTransfer.cpp"}
{"function": "setAttributeNodeNS", "filename": "Element.cpp"}
{"function": "item", "filename": "DOMStringList.cpp"}
{"function": "set", "filename": "URLSearchParams.cpp"}
{"function": "getModifierState", "filename": "MouseEvent.cpp"}
{"function": "newValueSpecifiedUnits", "filename": "SVGAngleTearOff.cpp"}
{"function": "initialize", "filename": "SVGNumberListTearOff.cpp"}
{"function": "initCustomEvent", "filename": "CustomEvent.cpp"}
{"function": "replaceState", "filename": "History.cpp"}
{"function": "createSVGTransform", "filename": "SVGSVGElement.cpp"}
{"function": "insertRow", "filename": "HTMLTableElement.cpp"}
{"function": "insertRule", "filename": "CSSStyleSheet.cpp"}
{"function": "fillText", "filename": "CanvasRenderingContext2D.cpp"}
{"function": "lock", "filename": "ScreenOrientation.cpp"}
{"function": "flipY", "filename": "DOMMatrixReadOnly.cpp"}
{"function": "item", "filename": "HTMLSelectElement.cpp"}
{"function": "getPathSegAtLength", "filename": "SVGPathElement.cpp"}
{"function": "generateKey", "filename": "SubtleCrypto.cpp"}
{"function": "addEventListener", "filename": "EventTarget.cpp"}
{"function": "deleteCaption", "filename": "HTMLTableElement.cpp"}
{"function": "getCTM", "filename": "SVGGraphicsElement.cpp"}
{"function": "pauseAnimations", "filename": "SVGSVGElement.cpp"}
{"function": "send", "filename": "DOMWebSocket.cpp"}
{"function": "go", "filename": "History.cpp"}
{"function": "createDocumentType", "filename": "DOMImplementation.cpp"}
{"function": "add", "filename": "HTMLOptionsCollection.cpp"}
{"function": "deriveBits", "filename": "SubtleCrypto.cpp"}
{"function": "setOrientToAngle", "filename": "SVGMarkerElement.cpp"}
{"function": "getItem", "filename": "SVGTransformListTearOff.cpp"}
{"function": "skewY", "filename": "SVGMatrixTearOff.cpp"}
{"function": "getClientRects", "filename": "Range.cpp"}
{"function": "isPointInRange", "filename": "Range.cpp"}
{"function": "delete", "filename": "CacheStorage.cpp"}
{"function": "scrollIntoView", "filename": "Element.cpp"}
{"function": "getNamedItem", "filename": "NamedNodeMap.cpp"}
{"function": "flipX", "filename": "SVGMatrixTearOff.cpp"}
{"function": "createEvent", "filename": "Document.cpp"}
{"function": "parseFromString", "filename": "DOMParser.cpp"}
{"function": "flipY", "filename": "SVGMatrixTearOff.cpp"}
{"function": "setRotate", "filename": "SVGTransformTearOff.cpp"}
{"function": "postMessage", "filename": "MessagePort.cpp"}
{"function": "item", "filename": "CSSStyleDeclaration.cpp"}
{"function": "readAsBinaryString", "filename": "FileReader.cpp"}
{"function": "splitText", "filename": "Text.cpp"}
{"function": "scale3dSelf", "filename": "DOMMatrix.cpp"}
{"function": "getAll", "filename": "FormData.cpp"}
{"function": "clear", "filename": "SVGPointListTearOff.cpp"}
{"function": "setSelectionRange", "filename": "HTMLInputElement.cpp"}
{"function": "endElement", "filename": "SVGAnimationElement.cpp"}
{"function": "canPlayType", "filename": "HTMLMediaElement.cpp"}
{"function": "addColorStop", "filename": "CanvasGradient.cpp"}
{"function": "removeListener", "filename": "MediaQueryList.cpp"}
{"function": "getCurrentTime", "filename": "SVGSVGElement.cpp"}
{"function": "item", "filename": "NamedNodeMap.cpp"}
{"function": "initCompositionEvent", "filename": "CompositionEvent.cpp"}
{"function": "appendItem", "filename": "SVGLengthListTearOff.cpp"}
{"function": "readAsArrayBuffer", "filename": "FileReader.cpp"}
{"function": "open", "filename": "IDBFactory.cpp"}
{"function": "cloneNode", "filename": "Node.cpp"}
{"function": "preventDefault", "filename": "Event.cpp"}
{"function": "collapse", "filename": "Range.cpp"}
{"function": "compareDocumentPosition", "filename": "Node.cpp"}
{"function": "unpauseAnimations", "filename": "SVGSVGElement.cpp"}
{"function": "insertNode", "filename": "Range.cpp"}
{"function": "scroll", "filename": "Element.cpp"}
{"function": "select", "filename": "HTMLInputElement.cpp"}
{"function": "importKey", "filename": "SubtleCrypto.cpp"}
{"function": "getComputedTextLength", "filename": "SVGTextContentElement.cpp"}
{"function": "enumerateDevices", "filename": "MediaDevices.cpp"}
{"function": "createContextualFragment", "filename": "Range.cpp"}
{"function": "getAudioTracks", "filename": "MediaStream.cpp"}
{"function": "deselectAll", "filename": "SVGSVGElement.cpp"}
{"function": "clear", "filename": "SVGNumberListTearOff.cpp"}
{"function": "appendChild", "filename": "Node.cpp"}
{"function": "scaleSelf", "filename": "DOMMatrix.cpp"}
{"function": "deleteDatabase", "filename": "IDBFactory.cpp"}
{"function": "setAttributeNode", "filename": "Element.cpp"}
{"function": "get", "filename": "URLSearchParams.cpp"}
{"function": "remove", "filename": "HTMLOptionsCollection.cpp"}
{"function": "setCustomValidity", "filename": "HTMLInputElement.cpp"}
{"function": "item", "filename": "DOMPlugin.cpp"}
{"function": "getModifierState", "filename": "KeyboardEvent.cpp"}
{"function": "detach", "filename": "Range.cpp"}
{"function": "getCharNumAtPosition", "filename": "SVGTextContentElement.cpp"}
{"function": "insertItemBefore", "filename": "SVGStringListTearOff.cpp"}
{"function": "getSVGDocument", "filename": "HTMLIFrameElement.cpp"}
{"function": "setMatrix", "filename": "SVGTransformTearOff.cpp"}
{"function": "createDocumentFragment", "filename": "Document.cpp"}
{"function": "beginElementAt", "filename": "SVGAnimationElement.cpp"}
{"function": "item", "filename": "MediaList.cpp"}
{"function": "getDistributedNodes", "filename": "HTMLContentElement.cpp"}
